aio_telegram/__init__.py
botgram-0.1.0a0.dist-info/LICENSE
botgram-0.1.0a0.dist-info/WHEEL
botgram-0.1.0a0.dist-info/METADATA
botgram-0.1.0a0.dist-info/RECORD
