Metadata-Version: 2.1
Name: botgram
Version: 0.1.0a0
Summary: Python aiohttp telegram SDK
License: MIT
Author: Denis Malin
Author-email: denis@malina.page
Requires-Python: >=3.6,<4.0
Classifier: License :: OSI Approved :: MIT License
Classifier: Programming Language :: Python :: 3
Classifier: Programming Language :: Python :: 3.10
Classifier: Programming Language :: Python :: 3.6
Classifier: Programming Language :: Python :: 3.7
Classifier: Programming Language :: Python :: 3.8
Classifier: Programming Language :: Python :: 3.9
Requires-Dist: aiohttp (>=3.8.0)
